pygloo.so
pygloo-0.2.1.dist-info/RECORD
pygloo-0.2.1.dist-info/METADATA
pygloo-0.2.1.dist-info/LICENSE
pygloo-0.2.1.dist-info/WHEEL
pygloo-0.2.1.dist-info/top_level.txt
