Metadata-Version: 2.1
Name: pygloo
Version: 0.2.1
Summary: A python binding for gloo
Home-page: https://github.com/ray-project/pygloo
Author: Ray Team
Author-email: ray-dev@googlegroups.com
License: Apache 2.0
Keywords: collective communication
Classifier: Programming Language :: Python :: 3
Classifier: Topic :: Scientific/Engineering :: Artificial Intelligence
License-File: LICENSE
